vdtk/__init__.py
vdtk/caption_metrics.py
vdtk/cli.py
vdtk/clip_recall.py
vdtk/concept_metrics.py
vdtk/content_recall.py
vdtk/core_set.py
vdtk/data_utils.py
vdtk/leave_one_out.py
vdtk/lm.py
vdtk/ngram_metrics.py
vdtk/qualitative_sample.py
vdtk/score.py
vdtk/semantic_variance.py
vdtk/stats_utils.py
vdtk/vocab_metrics.py
vdtk/assets/coco_labels.txt
vdtk/assets/imagenet_labels.txt
vdtk/assets/kinetics_400_labels.txt
vdtk/assets/kinetics_600_labels.txt
vdtk/assets/places_labels.txt
vdtk/metrics/bleu/LICENSE
vdtk/metrics/bleu/__init__.py
vdtk/metrics/bleu/bleu.py
vdtk/metrics/bleu/bleu_scorer.py
vdtk/metrics/cider/.gitignore
vdtk/metrics/cider/__init__.py
vdtk/metrics/cider/cider.py
vdtk/metrics/cider/cider_scorer.py
vdtk/metrics/cider/data/coco-val.pkl
vdtk/metrics/corenlp/.gitignore
vdtk/metrics/corenlp/__init__.py
vdtk/metrics/corenlp/lib/.gitattributes
vdtk/metrics/corenlp/lib/.gitkeep
vdtk/metrics/corenlp/lib/CORENLP_LICENSE
vdtk/metrics/corenlp/lib/METEOR_LICENSE
vdtk/metrics/corenlp/lib/Meteor-1.5.jar
vdtk/metrics/corenlp/lib/SPICE_LICENSE
vdtk/metrics/corenlp/lib/SceneGraphParser-1.0.jar
vdtk/metrics/corenlp/lib/ejml-0.23.jar
vdtk/metrics/corenlp/lib/fst-2.56.jar
vdtk/metrics/corenlp/lib/guava-19.0.jar
vdtk/metrics/corenlp/lib/hamcrest-core-1.3.jar
vdtk/metrics/corenlp/lib/jackson-core-2.8.8.jar
vdtk/metrics/corenlp/lib/javassist-3.21.0-GA.jar
vdtk/metrics/corenlp/lib/json-simple-1.1.1.jar
vdtk/metrics/corenlp/lib/junit-4.12.jar
vdtk/metrics/corenlp/lib/lmdbjni-0.4.6.jar
vdtk/metrics/corenlp/lib/lmdbjni-linux64-0.4.6.jar
vdtk/metrics/corenlp/lib/lmdbjni-osx64-0.4.6.jar
vdtk/metrics/corenlp/lib/lmdbjni-win64-0.4.6.jar
vdtk/metrics/corenlp/lib/objenesis-2.5.1.jar
vdtk/metrics/corenlp/lib/slf4j-api-1.7.9.jar
vdtk/metrics/corenlp/lib/slf4j-simple-1.7.9.jar
vdtk/metrics/corenlp/lib/spice-1.0.jar
vdtk/metrics/corenlp/lib/stanford-corenlp-3.6.0-models.jar
vdtk/metrics/corenlp/lib/stanford-corenlp-3.6.0.jar
vdtk/metrics/corenlp/lib/data/paraphrase-en.gz
vdtk-0.3.0.dist-info/LICENSE
vdtk-0.3.0.dist-info/METADATA
vdtk-0.3.0.dist-info/WHEEL
vdtk-0.3.0.dist-info/entry_points.txt
vdtk-0.3.0.dist-info/top_level.txt
vdtk-0.3.0.dist-info/RECORD
