Metadata-Version: 2.1
Name: vdtk
Version: 0.3.0
Summary: Visual Description Evaluation Toolkit
Author-email: David Chan <davidchan@berkeley.edu>
License: MIT
Classifier: Development Status :: 4 - Beta
Classifier: Intended Audience :: Science/Research
Classifier: Intended Audience :: Developers
Classifier: License :: OSI Approved :: MIT License
Classifier: Programming Language :: Python :: 3
Classifier: Programming Language :: Python :: 3.8
Classifier: Programming Language :: Python :: 3.9
Classifier: Programming Language :: Python :: 3.10
Classifier: Programming Language :: Python :: 3.11
Classifier: Topic :: Scientific/Engineering :: Artificial Intelligence
Classifier: Topic :: Scientific/Engineering :: Image Recognition
Classifier: Topic :: Scientific/Engineering :: Visualization
Classifier: Topic :: Scientific/Engineering :: Information Analysis
License-File: LICENSE
Requires-Dist: nltk (>=3.6.5)
Requires-Dist: numpy (>=1.21.4)
Requires-Dist: matplotlib (>=3.5.0)
Requires-Dist: tqdm (>=4.62.3)
Requires-Dist: spacy (>=3.2.0)
Requires-Dist: fuzzywuzzy (>=0.18.0)
Requires-Dist: rich (>=10.14.0)
Requires-Dist: mpire (>=2.3.1)
Requires-Dist: click (>=8.0.3)
Requires-Dist: fuzzysearch (>=0.7.3)
Requires-Dist: sentence-transformers (>=2.1.0)
Requires-Dist: bert-score (>=0.3.12)
Requires-Dist: embeddings (>=0.0.8)
Requires-Dist: POT (>=0.8)
Requires-Dist: rouge-score (>=0.1.2)
Requires-Dist: jdk4py (>=17.0.3.0)
Requires-Dist: mauve-text (>=0.3.0)
Requires-Dist: ftfy (>=6.1.1)
Requires-Dist: regex (>=2022.10.31)
Provides-Extra: all
Requires-Dist: pytest ; extra == 'all'
Requires-Dist: mypy ; extra == 'all'
Requires-Dist: black ; extra == 'all'
Requires-Dist: flake8 ; extra == 'all'
Requires-Dist: flake8-black ; extra == 'all'
Requires-Dist: isort ; extra == 'all'
Requires-Dist: tensorflow (>=2.11.0) ; extra == 'all'
Requires-Dist: tf-slim (>=1.1.0) ; extra == 'all'
Requires-Dist: sentencepiece (>=0.1.97) ; extra == 'all'
Requires-Dist: pandas (>=1.5.1) ; extra == 'all'
Requires-Dist: scipy (>=1.9.3) ; extra == 'all'
Provides-Extra: dev
Requires-Dist: pytest ; extra == 'dev'
Requires-Dist: mypy ; extra == 'dev'
Requires-Dist: black ; extra == 'dev'
Requires-Dist: flake8 ; extra == 'dev'
Requires-Dist: flake8-black ; extra == 'dev'
Requires-Dist: isort ; extra == 'dev'
Requires-Dist: pytest-xdist ; extra == 'dev'
